tartiflette_starlette/__init__.py
tartiflette_starlette-0.6.1.dist-info/LICENSE
tartiflette_starlette-0.6.1.dist-info/METADATA
tartiflette_starlette-0.6.1.dist-info/WHEEL
tartiflette_starlette-0.6.1.dist-info/top_level.txt
tartiflette_starlette-0.6.1.dist-info/RECORD
