Metadata-Version: 2.1
Name: tartiflette-starlette
Version: 0.6.1
Summary: (DEPRECATED) ASGI support for the Tartiflette Python GraphQL engine
Home-page: https://github.com/tartiflette/tartiflette-starlette
Author: Florimond Manca
Author-email: florimond.manca@gmail.com
License: MIT
Platform: UNKNOWN
Classifier: Development Status :: 7 - Inactive
Classifier: Operating System :: OS Independent
Classifier: Intended Audience :: Developers
Classifier: Topic :: Software Development :: Libraries
Classifier: Programming Language :: Python :: 3 :: Only
Classifier: Programming Language :: Python :: 3.6
Classifier: Programming Language :: Python :: 3.7
Classifier: Programming Language :: Python :: 3.8
Requires-Python: >=3.6
